fc_xd_bigdata3.py
fc_bigdata3-1.0.dist-info/METADATA
fc_bigdata3-1.0.dist-info/WHEEL
fc_bigdata3-1.0.dist-info/top_level.txt
fc_bigdata3-1.0.dist-info/RECORD
